clippie/__init__.py
clippie/image.py
clippie/model.py
clippie/nn.py
clippie/py.typed
clippie/tokeniser.py
clippie/util.py
clippie/data/vocab.pickle.gz
clippie/scripts/__init__.py
clippie/scripts/convert_vocab_file.py
clippie/scripts/convert_weights_file.py
mossblaser_clippie-0.0.3.dist-info/licenses/LICENSE
mossblaser_clippie-0.0.3.dist-info/METADATA
mossblaser_clippie-0.0.3.dist-info/WHEEL
mossblaser_clippie-0.0.3.dist-info/entry_points.txt
mossblaser_clippie-0.0.3.dist-info/top_level.txt
mossblaser_clippie-0.0.3.dist-info/RECORD
