Metadata-Version: 2.4
Name: mossblaser-clippie
Version: 0.0.3
Summary: A Numpy implementation of OpenAI's CLIP image and text encoding deep neural network
License:                     GNU GENERAL PUBLIC LICENSE
Project-URL: source, https://github.com/mossblaser/clippie
License-File: LICENSE
Requires-Dist: numpy
Requires-Dist: regex
Requires-Dist: pillow
Requires-Dist: weightie<1.0.0,>=0.0.1
Provides-Extra: convert
Requires-Dist: torch; extra == "convert"
Requires-Dist: torchvision; extra == "convert"
Dynamic: license-file
